{"subItptOf":"tdtl8MwK","canInterpretType":"my-mxp/v1/logopage-ObjectType","nameSelf":"my-mxp/v1/logopage","ownKVLs":[{"key":"InterpreterReferenceMapKey","value":{"tdtl8MwK":{"subItptOf":"metaexplorer.io/baseContainer","canInterpretType":"metaexplorer.io/ContainerObjType","nameSelf":"tdtl8MwK","ownKVLs":[{"key":"in_0","value":{"objRef":"1fddf4eb-9ec2-4642-a9f7-a7ce5d9cfd15","propRef":null},"ldType":"InterpreterClassType"},{"key":"in_1","value":{"objRef":"8ed6d4dd-905c-4d46-ae03-57393c64afa6","propRef":null},"ldType":"InterpreterClassType"},{"key":"in_2","value":{"objRef":"1a7ec58e-be8a-4937-9a92-f1d6936b9f93","propRef":null},"ldType":"InterpreterClassType"},{"key":"in_3","value":{"objRef":"7fa9d4bb-b90e-419d-bba6-a0455fa97c19","propRef":null},"ldType":"InterpreterClassType"},{"key":"in_4","value":{"objRef":"bd6c6c3a-ebdf-4514-ac3c-6ce0b3ee08bb","propRef":null},"ldType":"InterpreterClassType"}],"crudSkills":"cRud","inKeys":["in_0","in_1","in_2","in_3","in_4"]},"1fddf4eb-9ec2-4642-a9f7-a7ce5d9cfd15":{"subItptOf":"metaexplorer.io/imageDisplay","canInterpretType":"http://schema.org/ImageObject","nameSelf":"1fddf4eb-9ec2-4642-a9f7-a7ce5d9cfd15","ownKVLs":[{"key":"http://schema.org/contentUrl","value":"/media/react-logo.svg"},{"key":"CSSObjectFit","value":"contain"},{"key":"cssClass","value":"demo-img"}],"crudSkills":"cRud","inKeys":[]},"8ed6d4dd-905c-4d46-ae03-57393c64afa6":{"subItptOf":"metaexplorer.io/basichtml/italics","canInterpretType":"http://schema.org/Text","nameSelf":"8ed6d4dd-905c-4d46-ae03-57393c64afa6","ownKVLs":[{"key":"inputdata","value":"This app is built with React...","ldType":"http://schema.org/Text"}],"crudSkills":"cRud","inKeys":[]},"1a7ec58e-be8a-4937-9a92-f1d6936b9f93":{"subItptOf":"metaexplorer.io/imageDisplay","canInterpretType":"http://schema.org/ImageObject","nameSelf":"1a7ec58e-be8a-4937-9a92-f1d6936b9f93","ownKVLs":[{"key":"http://schema.org/contentUrl","value":"/media/metaexplorer-sketched-mini.jpg"},{"key":"CSSObjectFit","value":"contain"},{"key":"cssClass","value":"demo-img"}],"crudSkills":"cRud","inKeys":[]},"7fa9d4bb-b90e-419d-bba6-a0455fa97c19":{"subItptOf":"metaexplorer.io/basichtml/italics","canInterpretType":"http://schema.org/Text","nameSelf":"7fa9d4bb-b90e-419d-bba6-a0455fa97c19","ownKVLs":[{"key":"inputdata","value":"...and MetaExplorer, with more code or less code","ldType":"http://schema.org/Text"}],"crudSkills":"cRud","inKeys":[]},"bd6c6c3a-ebdf-4514-ac3c-6ce0b3ee08bb":{"subItptOf":"metaexplorer.io/basichtml/h3","canInterpretType":"http://schema.org/Text","nameSelf":"bd6c6c3a-ebdf-4514-ac3c-6ce0b3ee08bb","ownKVLs":[{"key":"inputdata","ldType":"http://schema.org/Text"}],"crudSkills":"cRud","inKeys":["inputdata"]}},"ldType":"InterpreterReferenceMapType"}],"crudSkills":"cRud","inKeys":[{"objRef":"bd6c6c3a-ebdf-4514-ac3c-6ce0b3ee08bb","propRef":"inputdata"}]}